dpnext/__init__.py
dpnext/settings.py
dpnext/__spec__/__init__.py
dpnext/__spec__/test_version.py
dpnext-0.1.0.dist-info/METADATA
dpnext-0.1.0.dist-info/WHEEL
dpnext-0.1.0.dist-info/entry_points.txt
dpnext-0.1.0.dist-info/RECORD
